pages2pdf.py
pages2pdf-0.0.16.dist-info/METADATA
pages2pdf-0.0.16.dist-info/WHEEL
pages2pdf-0.0.16.dist-info/entry_points.txt
pages2pdf-0.0.16.dist-info/RECORD
