Metadata-Version: 2.1
Name: pages2pdf
Version: 0.0.16
Summary: Converts .pages to .pdf
Project-URL: Homepage, https://github.com/blemli/pages2pdf
Project-URL: Issues, https://github.com/blemli/pages2pdf/issues
Author-email: Problemli GmbH <info@problem.li>
Classifier: License :: OSI Approved :: MIT License
Classifier: Operating System :: OS Independent
Classifier: Programming Language :: Python :: 3
Requires-Python: >=3.8
Requires-Dist: click>=8.1.7
Requires-Dist: cloudconvert>=2.1.0
Requires-Dist: python-dotenv>=1.0.1
